odoo/addons/shopinvader_address_shipping_note/README.rst
odoo/addons/shopinvader_address_shipping_note/__init__.py
odoo/addons/shopinvader_address_shipping_note/__manifest__.py
odoo/addons/shopinvader_address_shipping_note/i18n/shopinvader_address_shipping_note.pot
odoo/addons/shopinvader_address_shipping_note/models/__init__.py
odoo/addons/shopinvader_address_shipping_note/models/res_partner.py
odoo/addons/shopinvader_address_shipping_note/readme/CONTEXT.rst
odoo/addons/shopinvader_address_shipping_note/readme/CONTRIBUTORS.rst
odoo/addons/shopinvader_address_shipping_note/readme/DESCRIPTION.rst
odoo/addons/shopinvader_address_shipping_note/static/description/index.html
odoo/addons/shopinvader_address_shipping_note/views/res_partner.xml
odoo_addon_shopinvader_address_shipping_note-16.0.1.0.0.3.dist-info/METADATA
odoo_addon_shopinvader_address_shipping_note-16.0.1.0.0.3.dist-info/WHEEL
odoo_addon_shopinvader_address_shipping_note-16.0.1.0.0.3.dist-info/top_level.txt
odoo_addon_shopinvader_address_shipping_note-16.0.1.0.0.3.dist-info/RECORD
